submission_25_12_01_koellmann_vogt/submission/src/task7.1/counter_mod_k_count.sv
/**
 * Counter which has the number of elapsed clock cycles modulo k as output.
 *
 * @param i_clk input clock.
 * @param i_reset reset signal which resets the counter's value to zero.
 * @param i_k value k which is used for the modulo computation.
 * @param o_count set to number of elapsed clock cycles modulo k.
 **/
module counter_mod_k_count #(parameter N=8) ( input  logic         i_clk,
                                              input  logic         i_reset,
                                              input  logic [N-1:0] i_k,
                                              output logic [N-1:0] o_count );
  // current value of the counter
  logic [N-1:0] count;

  // on positive edge of input clock or reset
  // either reset counter or assign next value
  always_ff @(posedge i_clk, posedge i_reset)
    begin
      if( i_reset == 1'b1 )
        begin
          count <= {N{1'b0}};
        end
      else
        begin
          if( count == i_k-1 )
            begin
              count <= {N{1'b0}};
            end
          else
            begin
              count <= count + 1;
            end
        end
    end

  // assign output bus
  assign o_count = count;
endmodule

submission_25_12_01_koellmann_vogt/submission/src/task7.1/counter_mod_k_ro.sv
/**
 * Counter which has the rollover signal as output.
 * The signal o_roll_over is high in every clock cycle after a rollover occurred and low in all other cycles.
 *
 * Assume k=3, then:
 * cycle     | 0 | 1 | 2 | 3 | 4 | 5 | 6 | 7 | 8 | 9 | 10 | ...
 * mod k     | 0 | 1 | 2 | 0 | 1 | 2 | 0 | 1 | 2 | 0 |  1 | ...
 * rollover: | 0 | 0 | 0 | 1 | 0 | 0 | 1 | 0 | 0 | 1 |  0 | ...
 *
 *
 * @param i_clk input clock.
 * @param i_reset reset signal which resets the counter's value to zero.
 * @param i_k value k which is used for the modulo computation.
 * @param o_roll_over set to rollover signal which is high in every clock cycle after a rollover occurred; low else.
 **/
module counter_mod_k_ro #(parameter N=8) ( input  logic         i_clk,
                                           input  logic         i_reset,
                                           input  logic [N-1:0] i_k,
                                           output logic         o_roll_over );
  logic [N-1:0] count;

  counter_mod_k_count #(.N(N)) counter_inst (
    .i_clk(i_clk),
    .i_reset(i_reset),
    .i_k(i_k),
    .o_count(count)
  );

  // Rollover-Signal: high im Takt NACH dem Übergang von k-1 zu 0
  always_ff @(posedge i_clk, posedge i_reset)
  begin
    if (i_reset)
      o_roll_over <= 1'b0;
    else
      o_roll_over <= (count == i_k - 1);
  end
endmodule

submission_25_12_01_koellmann_vogt/src/task7.1/counter_mod_k_ro_tb.sv
/**
 * Testbench of the modulo-k counter which has the rollover signal as output.
 **/
module counter_mod_k_ro_tb;
  parameter N = 4;
  logic l_clk;
  logic l_reset;

  logic l_roll_over;
  logic [2:0] l_k;

  // reset
  initial
    begin
      l_reset <= 1;
      #3;
      l_reset <= 0;
    end

  counter_mod_k_ro #(.N(N)) dut ( .i_clk(l_clk),
                                  .i_reset(l_reset),
                                  .i_k(l_k),
                                  .o_roll_over(l_roll_over) );

  initial
    begin
      i_clk = 0;
      forever #5 i_clk = ~i_clk;
    end

  initial
    begin
      i_k = N;

      #10;
      assert( l_roll_over == 1'b0 )
      #10;
      assert( l_roll_over == 1'b0 )
      #10;
      assert( l_roll_over == 1'b0 )
      #10;
      assert( l_roll_over == 1'b1 )
      #10;
      assert( l_roll_over == 1'b0 )
      #10;
      assert( l_roll_over == 1'b0 )
      #10;
      assert( l_roll_over == 1'b0 )
      #10;
      assert( l_roll_over == 1'b1 )
      #10;
      assert( l_roll_over == 1'b0 )
      #10;
      assert( l_roll_over == 1'b0 )

      $finish;
    end
endmodule

submission_25_12_01_koellmann_vogt/src/dump_counter_mod_k_ro.vcd
$date
	Thu Nov 27 16:19:51 2025
$end
$version
	Icarus Verilog
$end
$timescale
	1s
$end
$scope module counter_mod_k_ro_tb $end
$var wire 1 ! l_roll_over $end
$var parameter 32 " N $end
$var reg 1 # l_clk $end
$var reg 3 $ l_k [2:0] $end
$var reg 1 % l_reset $end
$scope module dut $end
$var wire 1 # i_clk $end
$var wire 3 & i_k [2:0] $end
$var wire 1 % i_reset $end
$var wire 3 ' count [2:0] $end
$var parameter 32 ( N $end
$var reg 1 ! o_roll_over $end
$scope module counter_inst $end
$var wire 1 # i_clk $end
$var wire 3 ) i_k [2:0] $end
$var wire 1 % i_reset $end
$var wire 3 * o_count [2:0] $end
$var parameter 32 + N $end
$var reg 3 , count [2:0] $end
$upscope $end
$upscope $end
$upscope $end
$enddefinitions $end
$comment Show the parameter values. $end
$dumpall
b11 +
b11 (
b11 "
$end
#0
$dumpvars
b0 ,
b0 *
b100 )
b0 '
b100 &
1%
b100 $
0#
0!
$end
#3
0%
#5
b1 '
b1 *
b1 ,
1#
#10
0#
#15
b10 '
b10 *
b10 ,
1#
#20
0#
#25
b11 '
b11 *
b11 ,
1#
#30
0#
#35
b0 '
b0 *
b0 ,
1!
1#
#40
0#
#45
0!
b1 '
b1 *
b1 ,
1#
#50
0#
#55
b10 '
b10 *
b10 ,
1#
#60
0#
#65
b11 '
b11 *
b11 ,
1#
#70
0#
#75
b0 '
b0 *
b0 ,
1!
1#
#80
0#
#85
0!
b1 '
b1 *
b1 ,
1#
#90
0#
#95
b10 '
b10 *
b10 ,
1#
