submission_25_11_17_koellmann_vogt/src/task5.1/mux_2/mux_2.sv
module mux_2 #(parameter N=64) ( 
    input  logic [N-1:0] i_in0,
                         i_in1,
    input  logic         i_s,
    output logic [N-1:0] o_out 
);
    assign o_out = i_s ? i_in1 : i_in0;
endmodule

submission_25_11_17_koellmann_vogt/src/task5.1/mux_4/mux_4.sv
module mux_4 #(parameter N=64) ( 
    input  logic [N-1:0] i_in0,
                         i_in1,
                         i_in2,
                         i_in3,
    input  logic [1:0]   i_s,
    output logic [N-1:0] o_out 
);
    logic [N-1:0] l_mux_low, l_mux_high;
    
    // Erste Stufe: wählt zwischen in0/in1 und in2/in3
    mux_2 #(N) mux_low (
        .i_in0(i_in0),
        .i_in1(i_in1),
        .i_s  (i_s[0]),
        .o_out(l_mux_low)
    );
    
    mux_2 #(N) mux_high (
        .i_in0(i_in2),
        .i_in1(i_in3),
        .i_s  (i_s[0]),
        .o_out(l_mux_high)
    );
    
    // Zweite Stufe: wählt zwischen den Ergebnissen
    mux_2 #(N) mux_final (
        .i_in0(l_mux_low),
        .i_in1(l_mux_high),
        .i_s  (i_s[1]),
        .o_out(o_out)
    );
endmodule

submission_25_11_24_koellmann_vogt/src/task6.1/decoder_2_4/decoder_2_4.sv
module decoder_2_4( input  logic [1:0] i_binary,
                output logic [3:0] o_one_hot );
  always_comb
  begin
    case( i_binary )
      2'b00: o_one_hot = 4'b0001;
      2'b01: o_one_hot = 4'b0010;
      2'b10: o_one_hot = 4'b0100;
      2'b11: o_one_hot = 4'b1000;
      default: o_one_hot = 4'bxxxx;
    endcase
  end
endmodule

submission_25_11_24_koellmann_vogt/src/task6.1/sr_latch/sr_latch.sv
module sr_latch ( input logic i_r, i_s,
                  output logic o_q, o_qn );

    assign o_q = ~(i_r | o_qn);
    assign o_qn = ~(i_s | o_q);
endmodule

submission_25_11_24_koellmann_vogt/src/task6.1/d_latch/d_latch.sv
module d_latch ( input logic i_d, i_clk,
                 output logic o_q, o_qn );

    logic l_r, l_s;

    assign l_r = ~i_d & i_clk;
    assign l_s = i_d & i_clk;

    sr_latch sr_latch_inst ( .i_r(l_r), .i_s(l_s), .o_q(o_q), .o_qn(o_qn) );

endmodule

submission_25_11_24_koellmann_vogt/src/task6.1/d_latch/d_latch_tb.sv
module d_latch_tb;
    logic l_d, l_clk, l_q, l_qn;

    d_latch dut ( .i_d(l_d), .i_clk(l_clk), .o_q(l_q), .o_qn(l_qn) );

    initial l_clk = 0;
    always #5 l_clk = ~l_clk;

    initial begin
        $dumpfile("dump_d_latch.vcd");
        $dumpvars;

        l_d = 0;
        #10;
        assert (l_q === 0);
        assert (l_qn === 1);

        #2;
        l_d = 1;
        assert (l_q === 0);
        assert (l_qn === 1);

        #4;
        assert (l_q === 1);
        assert (l_qn === 0);

        l_d = 1;
        #6;
        assert (l_q === 1);
        assert (l_qn === 0);

        l_d = 0;
        #4;
        assert (l_q === 0);
        assert (l_qn === 1);

        #4;
        assert (l_q === 0);
        assert (l_qn === 1);

        l_d = 1;
        #6;
        assert (l_q === 1);
        assert (l_qn === 0);

        $finish;
    end
endmodule

submission_25_11_24_koellmann_vogt/src/task6.1/d_latch/dump_d_latch.vcd
$date
	Thu Nov 20 16:39:48 2025
$end
$version
	Icarus Verilog
$end
$timescale
	1s
$end
$scope module d_latch_tb $end
$var wire 1 ! l_qn $end
$var wire 1 " l_q $end
$var reg 1 # l_clk $end
$var reg 1 $ l_d $end
$scope module dut $end
$var wire 1 # i_clk $end
$var wire 1 $ i_d $end
$var wire 1 % l_r $end
$var wire 1 & l_s $end
$var wire 1 ! o_qn $end
$var wire 1 " o_q $end
$scope module sr_latch_inst $end
$var wire 1 % i_r $end
$var wire 1 & i_s $end
$var wire 1 " o_q $end
$var wire 1 ! o_qn $end
$upscope $end
$upscope $end
$upscope $end
$scope module decoder_2_4 $end
$var wire 2 ' i_binary [1:0] $end
$var reg 4 ( o_one_hot [3:0] $end
$upscope $end
$scope module mux_4 $end
$var wire 64 ) i_in0 [63:0] $end
$var wire 64 * i_in1 [63:0] $end
$var wire 64 + i_in2 [63:0] $end
$var wire 64 , i_in3 [63:0] $end
$var wire 2 - i_s [1:0] $end
$var wire 64 . o_out [63:0] $end
$var wire 64 / l_mux_low [63:0] $end
$var wire 64 0 l_mux_high [63:0] $end
$var parameter 32 1 N $end
$scope module mux_final $end
$var wire 1 2 i_s $end
$var wire 64 3 o_out [63:0] $end
$var wire 64 4 i_in1 [63:0] $end
$var wire 64 5 i_in0 [63:0] $end
$var parameter 32 6 N $end
$upscope $end
$scope module mux_high $end
$var wire 64 7 i_in0 [63:0] $end
$var wire 64 8 i_in1 [63:0] $end
$var wire 1 9 i_s $end
$var wire 64 : o_out [63:0] $end
$var parameter 32 ; N $end
$upscope $end
$scope module mux_low $end
$var wire 64 < i_in0 [63:0] $end
$var wire 64 = i_in1 [63:0] $end
$var wire 1 > i_s $end
$var wire 64 ? o_out [63:0] $end
$var parameter 32 @ N $end
$upscope $end
$upscope $end
$enddefinitions $end
$comment Show the parameter values. $end
$dumpall
b1000000 @
b1000000 ;
b1000000 6
b1000000 1
$end
#0
$dumpvars
bz ?
z>
bz =
bz <
bz :
z9
bz 8
bz 7
bz 5
bz 4
bz 3
z2
bz 0
bz /
bz .
bz -
bz ,
bz +
bz *
bz )
bx (
bz '
0&
0%
0$
0#
x"
x!
$end
#5
1!
0"
1%
1#
#10
0%
0#
#12
1$
#15
1"
0!
1&
1#
#20
0&
0#
#22
0$
#25
1!
0"
1%
1#
#30
0%
1$
0#
#35
1"
0!
1&
1#
