submission_25_11_03_koellmann_vogt/src/task3.3/ripple_carry_adder_4.sv
module full_adder(
        input  wire i_a,
                    i_b,
                    i_carry_in,
        output wire o_s,
                    o_carry_out
    );

    xor gate_s(o_s, i_a, i_b, i_carry_in);

    wire l_ab, l_ac, l_bc;

    and gate_ab(l_ab, i_a, i_b);
    and gate_ac(l_ac, i_a, i_carry_in);
    and gate_bc(l_bc, i_b, i_carry_in);

    or gate_cout(o_carry_out, l_ab, l_ac, l_bc);
endmodule

/**
 * 4-bit ripple-carry adder.
 *
 * @param i_a input A.
 * @param i_b input B.
 * @param i_carry_in carry in.
 * @param o_s sum.
 * @param o_carry_out carry out.
 **/
module ripple_carry_adder_4 (
        input  logic [3:0] i_a,
                           i_b,
        input  logic       i_carry_in,
        output logic [3:0] o_s,
        output logic       o_carry_out
    );

    wire carry1, carry2, carry3;

    full_adder adder1(
        .i_a(i_a[0:0]),
        .i_b(i_b[0:0]),
        .i_carry_in(i_carry_in),
        .o_s(o_s[0:0]),
        .o_carry_out(carry1)
    );

    full_adder adder2(
        .i_a(i_a[1:1]),
        .i_b(i_b[1:1]),
        .i_carry_in(carry1),
        .o_s(o_s[1:1]),
        .o_carry_out(carry2)
    );

    full_adder adder3(
        .i_a(i_a[2:2]),
        .i_b(i_b[2:2]),
        .i_carry_in(carry2),
        .o_s(o_s[2:2]),
        .o_carry_out(carry3)
    );

    full_adder adder4(
        .i_a(i_a[3:3]),
        .i_b(i_b[3:3]),
        .i_carry_in(carry3),
        .o_s(o_s[3:3]),
        .o_carry_out(o_carry_out)
    );

endmodule

submission_25_11_03_koellmann_vogt/src/task3.2/full_adder_tb.sv
/**
* Testbench of the gate-level full adder.
*/
module full_adder_tb;
    logic l_a, l_b, l_s;
    logic l_carry_in, l_carry_out;

    full_adder dut (
        .i_a        (l_a),
        .i_b        (l_b),
        .i_carry_in (l_carry_in),
        .o_s        (l_s),
        .o_carry_out(l_carry_out)
    );

    initial begin
        $dumpfile("dump_full_adder.vcd");
        $dumpvars;

        l_a = 1'b0;
        l_b = 1'b0;
        l_carry_in = 1'b0;
        #10;
        assert (l_s === 1'b0);
        assert (l_carry_out === 1'b0);

        l_a = 1'b1;
        l_b = 1'b0;
        l_carry_in = 1'b0;
        #10;
        assert (l_s === 1'b1);
        assert (l_carry_out === 1'b0);

        // TODO: add additional tests

        $finish;
    end
endmodule

submission_25_11_03_koellmann_vogt/src/task3.2/dump_full_adder.vcd
$date
	Thu Oct 30 12:14:59 2025
$end
$version
	Icarus Verilog
$end
$timescale
	1s
$end
$scope module full_adder_tb $end
$var wire 1 ! l_s $end
$var wire 1 " l_carry_out $end
$var reg 1 # l_a $end
$var reg 1 $ l_b $end
$var reg 1 % l_carry_in $end
$scope module dut $end
$var wire 1 # i_a $end
$var wire 1 $ i_b $end
$var wire 1 % i_carry_in $end
$var wire 1 & l_ab $end
$var wire 1 ' l_ac $end
$var wire 1 ( l_bc $end
$var wire 1 " o_carry_out $end
$var wire 1 ! o_s $end
$upscope $end
$upscope $end
$enddefinitions $end
$comment Show the parameter values. $end
$dumpall
$end
#0
$dumpvars
0(
0'
0&
0%
0$
0#
0"
0!
$end
#10
1!
1#
#20
1$
0#
#30
1%
0$
#40
1"
0!
1&
0%
1$
1#
#50
1'
0&
1%
0$
#60
1(
0'
1$
0#
#70
1!
1&
1'
1#
