submission_25_11_03_koellmann_vogt/src/task3.4/cla_block_4.sv
module cla_pre_4(
        input  wire [3:0] i_a,
                          i_b,
        output wire [3:0] o_g,
                          o_p
    );

    and gate_g0(o_g[0], i_a[0], i_b[0]);
    and gate_g1(o_g[1], i_a[1], i_b[1]);
    and gate_g2(o_g[2], i_a[2], i_b[2]);
    and gate_g3(o_g[3], i_a[3], i_b[3]);

    or gate_p0(o_p[0], i_a[0], i_b[0]);
    or gate_p1(o_p[1], i_a[1], i_b[1]);
    or gate_p2(o_p[2], i_a[2], i_b[2]);
    or gate_p3(o_p[3], i_a[3], i_b[3]);
endmodule

module cla_logic_4(
        input  wire [3:0] i_g,
                          i_p,
        output wire       o_g,
                          o_p
    );

    wire w1, w2, w3, w4, w5;

    and gate_and1(w1, i_g[0], i_p[1]);
    or gate_or1(w2, w1, i_g[1]);
    and gate_and2(w3, w2, i_p[2]);
    or gate_or2(w4, w3, i_g[2]);
    and gate_and3(w5, w4, i_p[3]);
    or gate_or3(o_g, w5, i_g[3]);

    and gate_p(o_p, i_p[0], i_p[1], i_p[2], i_p[3]);
endmodule

module cla_block_4()
endmodule

submission_25_11_03_koellmann_vogt/src/task3.4/cla_pre_4/cla_pre_4_tb.sv
/**
 * Testbench of the 4-bit CLA preprocessing stage.
 */
module cla_pre_4_tb;
    logic [3:0] l_a, l_b, l_g, l_p;

    cla_pre_4 dut(
        .i_a(l_a),
        .i_b(l_b),
        .o_g(l_g),
        .o_p(l_p)
    );

    initial begin
        $dumpfile("dump_cla_pre_4.vcd");
        $dumpvars;

        // Test 1: 0000 and 0000 -> G=0000, P=0000
        l_a = 4'b0000;
        l_b = 4'b0000;
        #10;
        assert (l_g === 4'b0000);
        assert (l_p === 4'b0000);

        // Test 2: 1111 and 0000 -> G=0000, P=1111
        l_a = 4'b1111;
        l_b = 4'b0000;
        #10;
        assert (l_g === 4'b0000);
        assert (l_p === 4'b1111);

        // Test 3: 0000 and 1111 -> G=0000, P=1111
        l_a = 4'b0000;
        l_b = 4'b1111;
        #10;
        assert (l_g === 4'b0000);
        assert (l_p === 4'b1111);

        // Test 4: 1111 and 1111 -> G=1111, P=1111
        l_a = 4'b1111;
        l_b = 4'b1111;
        #10;
        assert (l_g === 4'b1111);
        assert (l_p === 4'b1111);

        // Test 5: 1010 and 0101 -> G=0000, P=1111
        l_a = 4'b1010;
        l_b = 4'b0101;
        #10;
        assert (l_g === 4'b0000);
        assert (l_p === 4'b1111);

        // Test 6: 1100 and 1010 -> G=1000, P=1110
        l_a = 4'b1100;
        l_b = 4'b1010;
        #10;
        assert (l_g === 4'b1000);
        assert (l_p === 4'b1110);

        // Test 7: 0011 and 0110 -> G=0010, P=0111
        l_a = 4'b0011;
        l_b = 4'b0110;
        #10;
        assert (l_g === 4'b0010);
        assert (l_p === 4'b0111);

        // Test 8: 1001 and 1001 -> G=1001, P=1001
        l_a = 4'b1001;
        l_b = 4'b1001;
        #10;
        assert (l_g === 4'b1001);
        assert (l_p === 4'b1001);

        $finish;
    end
endmodule

submission_25_11_03_koellmann_vogt/src/task3.4/dump_cla_pre_4.vcd
$date
	Thu Oct 30 13:45:07 2025
$end
$version
	Icarus Verilog
$end
$timescale
	1s
$end
$scope module cla_pre_4_tb $end
$var wire 4 ! l_p [3:0] $end
$var wire 4 " l_g [3:0] $end
$var reg 4 # l_a [3:0] $end
$var reg 4 $ l_b [3:0] $end
$scope module dut $end
$var wire 4 % i_a [3:0] $end
$var wire 4 & i_b [3:0] $end
$var wire 4 ' o_p [3:0] $end
$var wire 4 ( o_g [3:0] $end
$upscope $end
$upscope $end
$enddefinitions $end
$comment Show the parameter values. $end
$dumpall
$end
#0
$dumpvars
b0 (
b0 '
b0 &
b0 %
b0 $
b0 #
b0 "
b0 !
$end
#10
b1111 !
b1111 '
b1111 #
b1111 %
#20
b1111 $
b1111 &
b0 #
b0 %
#30
b1111 "
b1111 (
b1111 #
b1111 %
#40
b0 "
b0 (
b101 $
b101 &
b1010 #
b1010 %
#50
b1000 "
b1000 (
b1110 !
b1110 '
b1010 $
b1010 &
b1100 #
b1100 %
#60
b10 "
b10 (
b111 !
b111 '
b110 $
b110 &
b11 #
b11 %
#70
b1001 "
b1001 (
b1001 !
b1001 '
b1001 $
b1001 &
b1001 #
b1001 %
