submission_25_12_01_koellmann_vogt/submission/src/task7.1/counter_mod_k_count.sv
/**
 * Counter which has the number of elapsed clock cycles modulo k as output.
 *
 * @param i_clk input clock.
 * @param i_reset reset signal which resets the counter's value to zero.
 * @param i_k value k which is used for the modulo computation.
 * @param o_count set to number of elapsed clock cycles modulo k.
 **/
module counter_mod_k_count #(parameter N=8) ( input  logic         i_clk,
                                              input  logic         i_reset,
                                              input  logic [N-1:0] i_k,
                                              output logic [N-1:0] o_count );
  // current value of the counter
  logic [N-1:0] count;

  // on positive edge of input clock or reset
  // either reset counter or assign next value
  always_ff @(posedge i_clk, posedge i_reset)
    begin
      if( i_reset == 1'b1 )
        begin
          count <= {N{1'b0}};
        end
      else
        begin
          if( count == i_k-1 )
            begin
              count <= {N{1'b0}};
            end
          else
            begin
              count <= count + 1;
            end
        end
    end

  // assign output bus
  assign o_count = count;
endmodule

submission_25_12_01_koellmann_vogt/submission/src/task7.1/counter_mod_k_ro.sv
/**
 * Counter which has the rollover signal as output.
 * The signal o_roll_over is high in every clock cycle after a rollover occurred and low in all other cycles.
 *
 * Assume k=3, then:
 * cycle     | 0 | 1 | 2 | 3 | 4 | 5 | 6 | 7 | 8 | 9 | 10 | ...
 * mod k     | 0 | 1 | 2 | 0 | 1 | 2 | 0 | 1 | 2 | 0 |  1 | ...
 * rollover: | 0 | 0 | 0 | 1 | 0 | 0 | 1 | 0 | 0 | 1 |  0 | ...
 *
 *
 * @param i_clk input clock.
 * @param i_reset reset signal which resets the counter's value to zero.
 * @param i_k value k which is used for the modulo computation.
 * @param o_roll_over set to rollover signal which is high in every clock cycle after a rollover occurred; low else.
 **/
module counter_mod_k_ro #(parameter N=8) ( input  logic         i_clk,
                                           input  logic         i_reset,
                                           input  logic [N-1:0] i_k,
                                           output logic         o_roll_over );
  logic [N-1:0] count;

  counter_mod_k_count #(.N(N)) counter_inst (
    .i_clk(i_clk),
    .i_reset(i_reset),
    .i_k(i_k),
    .o_count(count)
  );

  // Rollover-Signal: high im Takt NACH dem Übergang von k-1 zu 0
  always_ff @(posedge i_clk, posedge i_reset)
  begin
    if (i_reset)
      o_roll_over <= 1'b0;
    else
      o_roll_over <= (count == i_k - 1);
  end
endmodule

submission_25_12_01_koellmann_vogt/submission/src/task7.2/clock.sv
/**
 * Outputs a clock signal based on the given rollover signal.
 * The clock signal changes on every positive edge of the rollover signal.
 * On a positive edge of the reset signal, the clock is reset to high.
 *
 * @param i_roll_over rollover signal.
 * @param i_reset reset signal.
 * @param o_clk set to generated clock signal.
 **/
module clock( input  logic i_roll_over,
              input  logic i_reset,
              output logic o_clk );
  logic clk;

  always_ff @(posedge i_roll_over, posedge i_reset)
    begin
      if( i_reset == 1'b1 )
        begin
          clk <= 1'b1;
        end
      else
        begin
          clk <= ~clk;
        end
    end

  assign o_clk = clk;
endmodule

submission_25_12_01_koellmann_vogt/submission/src/task7.2/clock_tb.sv
/**
 * Testbench of the clock derived from a counter's rollover signal.
 **/
module clock_tb;
  logic l_reset;
  logic l_roll_over;
  logic l_clk;

  initial
    begin
      l_reset <= 1;
      #3;
      l_reset <= 0;
    end

  clock dut( .i_roll_over(l_roll_over),
             .i_reset(l_reset),
             .o_clk(l_clk) );

  initial begin
    $dumpfile("dump_clock.vcd");
    $dumpvars;

    l_roll_over = 1'b0;
    #10
    assert(l_clk === 1'b1);  // nach Reset: high
    #10
    assert(l_clk === 1'b1);

    l_roll_over = 1'b1;      // 1. posedge -> toggle zu low
    #5
    assert(l_clk === 1'b0);
    #5
    assert(l_clk === 1'b0);

    l_roll_over = 1'b0;
    #5
    assert(l_clk === 1'b0);
    #5
    assert(l_clk === 1'b0);

    l_roll_over = 1'b1;      // 2. posedge -> toggle zu high
    #5
    assert(l_clk === 1'b1);
    #5
    assert(l_clk === 1'b1);

    l_roll_over = 1'b0;
    #5
    assert(l_clk === 1'b1);
    #5
    assert(l_clk === 1'b1);

    l_roll_over = 1'b1;      // 3. posedge -> toggle zu low
    #5
    assert(l_clk === 1'b0);
    #5
    assert(l_clk === 1'b0);

    l_roll_over = 1'b0;
    #5
    assert(l_clk === 1'b0);
    #5
    assert(l_clk === 1'b0);

    $finish;
  end
endmodule

submission_25_12_01_koellmann_vogt/src/task7.2/dump_clock.vcd
$date
	Thu Nov 27 16:19:00 2025
$end
$version
	Icarus Verilog
$end
$timescale
	1s
$end
$scope module clock_tb $end
$var wire 1 ! l_clk $end
$var reg 1 " l_reset $end
$var reg 1 # l_roll_over $end
$scope module dut $end
$var wire 1 " i_reset $end
$var wire 1 # i_roll_over $end
$var wire 1 ! o_clk $end
$var reg 1 $ clk $end
$upscope $end
$upscope $end
$scope module counter_mod_k_ro $end
$var wire 1 % i_clk $end
$var wire 8 & i_k [7:0] $end
$var wire 1 ' i_reset $end
$var wire 8 ( count [7:0] $end
$var parameter 32 ) N $end
$var reg 1 * o_roll_over $end
$scope module counter_inst $end
$var wire 1 % i_clk $end
$var wire 8 + i_k [7:0] $end
$var wire 1 ' i_reset $end
$var wire 8 , o_count [7:0] $end
$var parameter 32 - N $end
$var reg 8 . count [7:0] $end
$upscope $end
$upscope $end
$enddefinitions $end
$comment Show the parameter values. $end
$dumpall
b1000 -
b1000 )
$end
#0
$dumpvars
bx .
bx ,
bz +
x*
bx (
z'
bz &
z%
1$
0#
1"
1!
$end
#3
0"
#20
0!
0$
1#
#30
0#
#40
1!
1$
1#
#50
0#
#60
0!
0$
1#
#70
0#
