submission_25_11_17_koellmann_vogt/submission/src/task5.3/xor_3/xor_3.sv
module xor_3 ( 
    input  logic i_in0,
                 i_in1,
                 i_in2,
    output logic o_res 
);
    assign o_res = i_in0 ^ i_in1 ^ i_in2;
endmodule

submission_25_11_17_koellmann_vogt/src/task5.3/xor_3/xor_3_tb.sv
module xor_3_tb;
    logic l_in0, l_in1, l_in2;
    logic l_res;

    xor_3 dut(
        .i_in0(l_in0),
        .i_in1(l_in1),
        .i_in2(l_in2),
        .o_res(l_res)
    );

    initial begin
        $dumpfile("dump_xor_3.vcd");
        $dumpvars(0, xor_3_tb);

        // Test alle 8 möglichen Kombinationen
        // XOR gibt 1 aus bei ungerader Anzahl von 1en

        // Test 1: 000 -> 0
        {l_in0, l_in1, l_in2} = 3'b000;
        #10;
        assert (l_res === 1'b0);

        // Test 2: 001 -> 1
        {l_in0, l_in1, l_in2} = 3'b001;
        #10;
        assert (l_res === 1'b1);

        // Test 3: 010 -> 1
        {l_in0, l_in1, l_in2} = 3'b010;
        #10;
        assert (l_res === 1'b1);

        // Test 4: 011 -> 0
        {l_in0, l_in1, l_in2} = 3'b011;
        #10;
        assert (l_res === 1'b0);

        // Test 5: 100 -> 1
        {l_in0, l_in1, l_in2} = 3'b100;
        #10;
        assert (l_res === 1'b1);

        // Test 6: 101 -> 0
        {l_in0, l_in1, l_in2} = 3'b101;
        #10;
        assert (l_res === 1'b0);

        // Test 7: 110 -> 0
        {l_in0, l_in1, l_in2} = 3'b110;
        #10;
        assert (l_res === 1'b0);

        // Test 8: 111 -> 1
        {l_in0, l_in1, l_in2} = 3'b111;
        #10;
        assert (l_res === 1'b1);
        $finish;
    end

endmodule

submission_25_11_17_koellmann_vogt/src/task5.3/dump_xor_3.vcd
$date
	Thu Nov 13 16:54:17 2025
$end
$version
	Icarus Verilog
$end
$timescale
	1s
$end
$scope module xor_3_tb $end
$var wire 1 ! l_res $end
$var reg 1 " l_in0 $end
$var reg 1 # l_in1 $end
$var reg 1 $ l_in2 $end
$scope module dut $end
$var wire 1 " i_in0 $end
$var wire 1 # i_in1 $end
$var wire 1 $ i_in2 $end
$var wire 1 ! o_res $end
$upscope $end
$upscope $end
$enddefinitions $end
$comment Show the parameter values. $end
$dumpall
$end
#0
$dumpvars
0$
0#
0"
0!
$end
#10
1!
1$
#20
1!
1#
0$
#30
0!
1$
#40
1!
1"
0#
0$
#50
0!
1$
#60
0!
1#
0$
#70
1!
1$
