submission_25_11_03_koellmann_vogt/src/task3.4/cla_block_4.sv
module cla_pre_4(
        input  wire [3:0] i_a,
                          i_b,
        output wire [3:0] o_g,
                          o_p
    );

    and gate_g0(o_g[0], i_a[0], i_b[0]);
    and gate_g1(o_g[1], i_a[1], i_b[1]);
    and gate_g2(o_g[2], i_a[2], i_b[2]);
    and gate_g3(o_g[3], i_a[3], i_b[3]);

    or gate_p0(o_p[0], i_a[0], i_b[0]);
    or gate_p1(o_p[1], i_a[1], i_b[1]);
    or gate_p2(o_p[2], i_a[2], i_b[2]);
    or gate_p3(o_p[3], i_a[3], i_b[3]);
endmodule

module cla_logic_4(
        input  wire [3:0] i_g,
                          i_p,
        output wire       o_g,
                          o_p
    );

    wire w1, w2, w3, w4, w5;

    and gate_and1(w1, i_g[0], i_p[1]);
    or gate_or1(w2, w1, i_g[1]);
    and gate_and2(w3, w2, i_p[2]);
    or gate_or2(w4, w3, i_g[2]);
    and gate_and3(w5, w4, i_p[3]);
    or gate_or3(o_g, w5, i_g[3]);

    and gate_p(o_p, i_p[0], i_p[1], i_p[2], i_p[3]);
endmodule

module cla_block_4()
endmodule

submission_25_11_03_koellmann_vogt/src/task3.4/cla_logic_4_tb.sv
/**
 * Testbench of the 4-bit CLA logic stage.
 */
module cla_logic_4_tb;
    logic [3:0] l_g, l_p;
    logic l_g_out, l_p_out;

    cla_logic_4 dut(
        .i_g(l_g),
        .i_p(l_p),
        .o_g(l_g_out),
        .o_p(l_p_out)
    );

    initial begin
        $dumpfile("dump_cla_logic_4.vcd");
        $dumpvars;

        // Test 1: All zeros -> G=0, P=0
        l_g = 4'b0000;
        l_p = 4'b0000;
        #10;
        assert (l_g_out === 1'b0);
        assert (l_p_out === 1'b0);

        // Test 2: G3=1, all P=0 -> G=1, P=0
        l_g = 4'b1000;
        l_p = 4'b0000;
        #10;
        assert (l_g_out === 1'b1);
        assert (l_p_out === 1'b0);

        // Test 3: All P=1, G=0 -> G=0, P=1
        l_g = 4'b0000;
        l_p = 4'b1111;
        #10;
        assert (l_g_out === 1'b0);
        assert (l_p_out === 1'b1);

        // Test 4: All ones -> G=1, P=1
        l_g = 4'b1111;
        l_p = 4'b1111;
        #10;
        assert (l_g_out === 1'b1);
        assert (l_p_out === 1'b1);

        l_g = 4'b0001;
        l_p = 4'b1110;
        #10;
        assert (l_g_out === 1'b1);
        assert (l_p_out === 1'b0);

        l_g = 4'b0010;
        l_p = 4'b1100;
        #10;
        assert (l_g_out === 1'b1);
        assert (l_p_out === 1'b0);

        l_g = 4'b0100;
        l_p = 4'b1000;
        #10;
        assert (l_g_out === 1'b1);
        assert (l_p_out === 1'b0);

        l_g = 4'b0001;
        l_p = 4'b0000;
        #10;
        assert (l_g_out === 1'b0);
        assert (l_p_out === 1'b0);

        l_g = 4'b0010;
        l_p = 4'b0100;
        #10;
        assert (l_g_out === 1'b0);
        assert (l_p_out === 1'b0);

        l_g = 4'b0101;
        l_p = 4'b1010;
        #10;
        assert (l_g_out === 1'b1);
        assert (l_p_out === 1'b0);

        $finish;
    end
endmodule

submission_25_11_03_koellmann_vogt/submission/src/task3.4/cla_logic_4/dump_cla_logic_4.vcd
$date
	Thu Oct 30 13:55:20 2025
$end
$version
	Icarus Verilog
$end
$timescale
	1s
$end
$scope module cla_logic_4_tb $end
$var wire 1 ! l_p_out $end
$var wire 1 " l_g_out $end
$var reg 4 # l_g [3:0] $end
$var reg 4 $ l_p [3:0] $end
$scope module dut $end
$var wire 4 % i_g [3:0] $end
$var wire 4 & i_p [3:0] $end
$var wire 1 " o_g $end
$var wire 1 ! o_p $end
$var wire 1 ' w1 $end
$var wire 1 ( w2 $end
$var wire 1 ) w3 $end
$var wire 1 * w4 $end
$var wire 1 + w5 $end
$upscope $end
$upscope $end
$enddefinitions $end
$comment Show the parameter values. $end
$dumpall
$end
#0
$dumpvars
0+
0*
0)
0(
0'
b0 &
b0 %
b0 $
b0 #
0"
0!
$end
#10
1"
b1000 #
b1000 %
#20
1!
0"
b1111 $
b1111 &
b0 #
b0 %
#30
1)
1+
1'
1(
1*
1"
b1111 #
b1111 %
#40
0!
b1110 $
b1110 &
b1 #
b1 %
#50
0'
b1100 $
b1100 &
b10 #
b10 %
#60
0)
0(
b1000 $
b1000 &
b100 #
b100 %
#70
0"
0+
0*
b0 $
b0 &
b1 #
b1 %
#80
1*
1)
1(
b100 $
b100 &
b10 #
b10 %
#90
1"
0)
1+
1'
1(
b1010 $
b1010 &
b101 #
b101 %
