submission_25_11_17_koellmann_vogt/src/task5.1/adder/adder.sv
module adder #(parameter N=64) ( 
    input  logic [N-1:0] i_a,
                         i_b,
    input  logic         i_carry_in,
    output logic [N-1:0] o_s,
    output logic         o_carry_out 
);
    assign {o_carry_out, o_s} = i_a + i_b + i_carry_in;
endmodule

submission_25_11_17_koellmann_vogt/submission/src/task5.1/adder/adder_tb.sv
/**
 * Testbench for the 64-bit carry-lookahead adder.
 */
module adder_tb;
    parameter N = 64;
    
    logic [N-1:0] l_a, l_b, l_s;
    logic l_carry_in, l_carry_out;

    adder #(N) dut(
        .i_a        (l_a),
        .i_b        (l_b),
        .i_carry_in (l_carry_in),
        .o_s        (l_s),
        .o_carry_out(l_carry_out)
    );

    initial begin
        $dumpfile("dump_adder.vcd");
        $dumpvars;

        // Test 1: 0 + 0 + 0 = 0, Cout=0
        l_a = 64'h0;
        l_b = 64'h0;
        l_carry_in = 1'b0;
        #10;
        assert (l_s === 64'h0);
        assert (l_carry_out === 1'b0);

        // Test 2: Simple addition without carry out
        l_a = 64'h12345678;
        l_b = 64'h87654321;
        l_carry_in = 1'b0;
        #10;
        assert (l_s === 64'h99999999);
        assert (l_carry_out === 1'b0);

        // Test 3: Addition with carry in
        l_a = 64'hAAAAAAAAAAAAAAAA;
        l_b = 64'h5555555555555554;
        l_carry_in = 1'b1;
        #10;
        assert (l_s === 64'hFFFFFFFFFFFFFFFF);
        assert (l_carry_out === 1'b0);

        // Test 4: Maximum values causing overflow
        l_a = 64'hFFFFFFFFFFFFFFFF;
        l_b = 64'h0;
        l_carry_in = 1'b1;
        #10;
        assert (l_s === 64'h0);
        assert (l_carry_out === 1'b1);

        // Test 5: Another overflow case
        l_a = 64'hFFFFFFFFFFFFFFFF;
        l_b = 64'hFFFFFFFFFFFFFFFF;
        l_carry_in = 1'b0;
        #10;
        assert (l_s === 64'hFFFFFFFFFFFFFFFE);
        assert (l_carry_out === 1'b1);

        // Test 6: Maximum overflow
        l_a = 64'hFFFFFFFFFFFFFFFF;
        l_b = 64'hFFFFFFFFFFFFFFFF;
        l_carry_in = 1'b1;
        #10;
        assert (l_s === 64'hFFFFFFFFFFFFFFFF);
        assert (l_carry_out === 1'b1);

        // Test 7: Random large numbers
        l_a = 64'h123456789ABCDEF0;
        l_b = 64'hFEDCBA9876543210;
        l_carry_in = 1'b0;
        #10;
        assert (l_s === 64'h1111111111111100);
        assert (l_carry_out === 1'b1);

        // Test 8: Alternating bit patterns
        l_a = 64'hA5A5A5A5A5A5A5A5;
        l_b = 64'h5A5A5A5A5A5A5A5A;
        l_carry_in = 1'b0;
        #10;
        assert (l_s === 64'hFFFFFFFFFFFFFFFF);
        assert (l_carry_out === 1'b0);
        $finish;
    end
endmodule

submission_25_11_17_koellmann_vogt/src/task5.1/adder/dump_adder.vcd
$date
	Thu Nov 13 16:38:57 2025
$end
$version
	Icarus Verilog
$end
$timescale
	1s
$end
$scope module adder_tb $end
$var wire 64 ! l_s [63:0] $end
$var wire 1 " l_carry_out $end
$var parameter 32 # N $end
$var reg 64 $ l_a [63:0] $end
$var reg 64 % l_b [63:0] $end
$var reg 1 & l_carry_in $end
$scope module dut $end
$var wire 64 ' i_a [63:0] $end
$var wire 64 ( i_b [63:0] $end
$var wire 1 & i_carry_in $end
$var wire 64 ) o_s [63:0] $end
$var wire 1 " o_carry_out $end
$var parameter 32 * N $end
$upscope $end
$upscope $end
$enddefinitions $end
$comment Show the parameter values. $end
$dumpall
b1000000 *
b1000000 #
$end
#0
$dumpvars
b0 )
b0 (
b0 '
0&
b0 %
b0 $
0"
b0 !
$end
#10
b10011001100110011001100110011001 !
b10011001100110011001100110011001 )
b10000111011001010100001100100001 %
b10000111011001010100001100100001 (
b10010001101000101011001111000 $
b10010001101000101011001111000 '
#20
b1111111111111111111111111111111111111111111111111111111111111111 !
b1111111111111111111111111111111111111111111111111111111111111111 )
1&
b101010101010101010101010101010101010101010101010101010101010100 %
b101010101010101010101010101010101010101010101010101010101010100 (
b1010101010101010101010101010101010101010101010101010101010101010 $
b1010101010101010101010101010101010101010101010101010101010101010 '
#30
b0 !
b0 )
1"
b0 %
b0 (
b1111111111111111111111111111111111111111111111111111111111111111 $
b1111111111111111111111111111111111111111111111111111111111111111 '
#40
b1111111111111111111111111111111111111111111111111111111111111110 !
b1111111111111111111111111111111111111111111111111111111111111110 )
0&
b1111111111111111111111111111111111111111111111111111111111111111 %
b1111111111111111111111111111111111111111111111111111111111111111 (
#50
b1111111111111111111111111111111111111111111111111111111111111111 !
b1111111111111111111111111111111111111111111111111111111111111111 )
1&
#60
b1000100010001000100010001000100010001000100010001000100000000 !
b1000100010001000100010001000100010001000100010001000100000000 )
0&
b1111111011011100101110101001100001110110010101000011001000010000 %
b1111111011011100101110101001100001110110010101000011001000010000 (
b1001000110100010101100111100010011010101111001101111011110000 $
b1001000110100010101100111100010011010101111001101111011110000 '
#70
0"
b1111111111111111111111111111111111111111111111111111111111111111 !
b1111111111111111111111111111111111111111111111111111111111111111 )
b101101001011010010110100101101001011010010110100101101001011010 %
b101101001011010010110100101101001011010010110100101101001011010 (
b1010010110100101101001011010010110100101101001011010010110100101 $
b1010010110100101101001011010010110100101101001011010010110100101 '
