submission_25_11_17_koellmann_vogt/src/task5.1/mux_2/mux_2.sv
module mux_2 #(parameter N=64) ( 
    input  logic [N-1:0] i_in0,
                         i_in1,
    input  logic         i_s,
    output logic [N-1:0] o_out 
);
    assign o_out = i_s ? i_in1 : i_in0;
endmodule

submission_25_11_17_koellmann_vogt/src/task5.1/mux_4/mux_4.sv
module mux_4 #(parameter N=64) ( 
    input  logic [N-1:0] i_in0,
                         i_in1,
                         i_in2,
                         i_in3,
    input  logic [1:0]   i_s,
    output logic [N-1:0] o_out 
);
    logic [N-1:0] l_mux_low, l_mux_high;
    
    // Erste Stufe: wählt zwischen in0/in1 und in2/in3
    mux_2 #(N) mux_low (
        .i_in0(i_in0),
        .i_in1(i_in1),
        .i_s  (i_s[0]),
        .o_out(l_mux_low)
    );
    
    mux_2 #(N) mux_high (
        .i_in0(i_in2),
        .i_in1(i_in3),
        .i_s  (i_s[0]),
        .o_out(l_mux_high)
    );
    
    // Zweite Stufe: wählt zwischen den Ergebnissen
    mux_2 #(N) mux_final (
        .i_in0(l_mux_low),
        .i_in1(l_mux_high),
        .i_s  (i_s[1]),
        .o_out(o_out)
    );
endmodule

submission_25_11_24_koellmann_vogt/src/task6.1/decoder_2_4/decoder_2_4.sv
module decoder_2_4( input  logic [1:0] i_binary,
                output logic [3:0] o_one_hot );
  always_comb
  begin
    case( i_binary )
      2'b00: o_one_hot = 4'b0001;
      2'b01: o_one_hot = 4'b0010;
      2'b10: o_one_hot = 4'b0100;
      2'b11: o_one_hot = 4'b1000;
      default: o_one_hot = 4'bxxxx;
    endcase
  end
endmodule

submission_25_11_24_koellmann_vogt/src/task6.1/sr_latch/sr_latch.sv
module sr_latch ( input logic i_r, i_s,
                  output logic o_q, o_qn );

    assign o_q = ~(i_r | o_qn);
    assign o_qn = ~(i_s | o_q);
endmodule

submission_25_11_24_koellmann_vogt/src/task6.1/d_latch/d_latch.sv
module d_latch ( input logic i_d, i_clk,
                 output logic o_q, o_qn );

    logic l_r, l_s;

    assign l_r = ~i_d & i_clk;
    assign l_s = i_d & i_clk;

    sr_latch sr_latch_inst ( .i_r(l_r), .i_s(l_s), .o_q(o_q), .o_qn(o_qn) );

endmodule

submission_25_11_24_koellmann_vogt/submission/src/task6.1/d_flip_flop/d_flip_flop.sv
module d_flip_flop ( input logic i_d, i_clk,
                     output logic o_q, o_qn );

    logic l_primary_q, l_primary_qn;
    
    d_latch d_latch_primary ( .i_d(i_d), .i_clk(~i_clk), .o_q(l_primary_q), .o_qn(l_primary_qn) );
    d_latch d_latch_secondary ( .i_d(l_primary_q), .i_clk(i_clk), .o_q(o_q), .o_qn(o_qn) );
endmodule

submission_25_11_24_koellmann_vogt/src/task6.1/d_flip_flop/d_flip_flop_tb.sv
module d_flip_flop_tb;
    logic l_d, l_clk, l_q, l_qn;

    d_flip_flop dut ( .i_d(l_d), .i_clk(l_clk), .o_q(l_q), .o_qn(l_qn) );

    initial l_clk = 0;
    always #5 l_clk = ~l_clk;

    initial begin
        $dumpfile("dump_d_flip_flop.vcd");
        $dumpvars;

        l_d = 0;
        #10;
        assert (l_q === 0);
        assert (l_qn === 1);

        l_d = 1;
        #3;
        assert (l_q === 0);
        assert (l_qn === 1);

        #7;
        assert (l_q === 1);
        assert (l_qn === 0);

        l_d = 0;
        #3;
        assert (l_q === 1);
        assert (l_qn === 0);

        #7;
        assert (l_q === 0);
        assert (l_qn === 1);

        l_d = 1;
        #10;
        assert (l_q === 1);
        assert (l_qn === 0);

        l_d = 0;
        #10;
        assert (l_q === 0);
        assert (l_qn === 1);

        $finish;
    end
endmodule

submission_25_11_24_koellmann_vogt/src/task6.1/d_flip_flop/dump_d_flip_flop.vcd
$date
	Thu Nov 20 16:41:00 2025
$end
$version
	Icarus Verilog
$end
$timescale
	1s
$end
$scope module d_flip_flop_tb $end
$var wire 1 ! l_qn $end
$var wire 1 " l_q $end
$var reg 1 # l_clk $end
$var reg 1 $ l_d $end
$scope module dut $end
$var wire 1 # i_clk $end
$var wire 1 $ i_d $end
$var wire 1 ! o_qn $end
$var wire 1 " o_q $end
$var wire 1 % l_primary_qn $end
$var wire 1 & l_primary_q $end
$scope module d_latch_primary $end
$var wire 1 ' i_clk $end
$var wire 1 $ i_d $end
$var wire 1 ( l_r $end
$var wire 1 ) l_s $end
$var wire 1 % o_qn $end
$var wire 1 & o_q $end
$scope module sr_latch_inst $end
$var wire 1 ( i_r $end
$var wire 1 ) i_s $end
$var wire 1 & o_q $end
$var wire 1 % o_qn $end
$upscope $end
$upscope $end
$scope module d_latch_secondary $end
$var wire 1 # i_clk $end
$var wire 1 & i_d $end
$var wire 1 * l_r $end
$var wire 1 + l_s $end
$var wire 1 ! o_qn $end
$var wire 1 " o_q $end
$scope module sr_latch_inst $end
$var wire 1 * i_r $end
$var wire 1 + i_s $end
$var wire 1 " o_q $end
$var wire 1 ! o_qn $end
$upscope $end
$upscope $end
$upscope $end
$upscope $end
$scope module decoder_2_4 $end
$var wire 2 , i_binary [1:0] $end
$var reg 4 - o_one_hot [3:0] $end
$upscope $end
$scope module mux_4 $end
$var wire 64 . i_in0 [63:0] $end
$var wire 64 / i_in1 [63:0] $end
$var wire 64 0 i_in2 [63:0] $end
$var wire 64 1 i_in3 [63:0] $end
$var wire 2 2 i_s [1:0] $end
$var wire 64 3 o_out [63:0] $end
$var wire 64 4 l_mux_low [63:0] $end
$var wire 64 5 l_mux_high [63:0] $end
$var parameter 32 6 N $end
$scope module mux_final $end
$var wire 1 7 i_s $end
$var wire 64 8 o_out [63:0] $end
$var wire 64 9 i_in1 [63:0] $end
$var wire 64 : i_in0 [63:0] $end
$var parameter 32 ; N $end
$upscope $end
$scope module mux_high $end
$var wire 64 < i_in0 [63:0] $end
$var wire 64 = i_in1 [63:0] $end
$var wire 1 > i_s $end
$var wire 64 ? o_out [63:0] $end
$var parameter 32 @ N $end
$upscope $end
$scope module mux_low $end
$var wire 64 A i_in0 [63:0] $end
$var wire 64 B i_in1 [63:0] $end
$var wire 1 C i_s $end
$var wire 64 D o_out [63:0] $end
$var parameter 32 E N $end
$upscope $end
$upscope $end
$enddefinitions $end
$comment Show the parameter values. $end
$dumpall
b1000000 E
b1000000 @
b1000000 ;
b1000000 6
$end
#0
$dumpvars
bz D
zC
bz B
bz A
bz ?
z>
bz =
bz <
bz :
bz 9
bz 8
z7
bz 5
bz 4
bz 3
bz 2
bz 1
bz 0
bz /
bz .
bx -
bz ,
0+
0*
0)
1(
1'
0&
1%
0$
0#
x"
x!
$end
#5
1!
0(
0"
0'
1*
1#
#10
1&
0%
1)
1'
0*
0#
1$
#15
1"
0)
0!
0'
1+
1#
#20
1%
0&
1(
1'
0+
0#
0$
#25
1!
0(
0"
0'
1*
1#
#30
1&
0%
1)
1'
0*
0#
1$
#35
1"
0)
0!
0'
1+
1#
#40
1%
0&
1(
1'
0+
0#
0$
#45
1!
0(
0"
0'
1*
1#
#50
1(
1'
0*
0#
